python_odds/__init__.py
python_odds/sportsbet/__init__.py
python_odds/sportsbet/api.py
python_odds-0.2.1.dist-info/METADATA
python_odds-0.2.1.dist-info/WHEEL
python_odds-0.2.1.dist-info/RECORD
