Metadata-Version: 2.1
Name: python-odds
Version: 0.2.1
Summary: 
Author: Sander
Author-email: spmvoss@gmail.com
Requires-Python: >=3.11,<4.0
Classifier: Programming Language :: Python :: 3
Classifier: Programming Language :: Python :: 3.11
Requires-Dist: loguru (>=0.7.2,<0.8.0)
Requires-Dist: pytest (>=7.4.3,<8.0.0)
Requires-Dist: requests (>=2.31.0,<3.0.0)
